{
  "version": "1.0",
  "defaultProvider": "cdnjs",
  "libraries": [
    {
      "library": "jquery@3.5.1",
      "destination": "wwwroot/lib/jquery/"
    },
    {
      "library": "jquery-validation-unobtrusive@3.2.12",
      "destination": "wwwroot/lib/jquery-validation-unobtrusive/",
      "files": [
        "jquery.validate.unobtrusive.min.js"
      ]
    },
    {
      "library": "jquery-validate@1.19.2",
      "destination": "wwwroot/lib/jquery-validate/"
    },
    {
      "library": "twitter-bootstrap@4.6.0",
      "destination": "wwwroot/lib/bootstrap/"
    },
    {
      "library": "popper.js@2.9.0",
      "destination": "wwwroot/lib/popper.js/"
    },
    {
      "library": "bootstrap-select@1.13.18",
      "destination": "wwwroot/bootstrap-select/"
    }
  ]
}